odoo/addons/ai_oca_native_generate_ollama/README.rst
odoo/addons/ai_oca_native_generate_ollama/__init__.py
odoo/addons/ai_oca_native_generate_ollama/__manifest__.py
odoo/addons/ai_oca_native_generate_ollama/controllers/__init__.py
odoo/addons/ai_oca_native_generate_ollama/controllers/main.py
odoo/addons/ai_oca_native_generate_ollama/i18n/ai_oca_native_generate_ollama.pot
odoo/addons/ai_oca_native_generate_ollama/i18n/it.po
odoo/addons/ai_oca_native_generate_ollama/readme/CONFIGURE.md
odoo/addons/ai_oca_native_generate_ollama/readme/CONTEXT.md
odoo/addons/ai_oca_native_generate_ollama/readme/CONTRIBUTORS.md
odoo/addons/ai_oca_native_generate_ollama/readme/DESCRIPTION.md
odoo/addons/ai_oca_native_generate_ollama/static/description/icon.png
odoo/addons/ai_oca_native_generate_ollama/static/description/index.html
odoo/addons/ai_oca_native_generate_ollama/tests/__init__.py
odoo/addons/ai_oca_native_generate_ollama/tests/test_ollama.py
odoo_addon_ai_oca_native_generate_ollama-18.0.1.0.0.3.dist-info/METADATA
odoo_addon_ai_oca_native_generate_ollama-18.0.1.0.0.3.dist-info/WHEEL
odoo_addon_ai_oca_native_generate_ollama-18.0.1.0.0.3.dist-info/top_level.txt
odoo_addon_ai_oca_native_generate_ollama-18.0.1.0.0.3.dist-info/RECORD
