Metadata-Version: 2.1
Name: odoo-addon-ai_oca_native_generate_ollama
Version: 18.0.1.0.0.3
Requires-Python: >=3.10
Requires-Dist: odoo==18.0.*
Requires-Dist: ollama
Summary: This module replaces AI from html_editor to use an Ollama server instead of OpenAI through Odoo IAP.
Home-page: https://github.com/OCA/ai
License: AGPL-3
Author: Dixmit,Odoo Community Association (OCA)
Author-email: support@odoo-community.org
Classifier: Programming Language :: Python
Classifier: Framework :: Odoo
Classifier: Framework :: Odoo :: 18.0
Classifier: License :: OSI Approved :: GNU Affero General Public License v3
